J4useragent/J4useragent.py
J4useragent/__init__.py
j4useragent-0.1.2.dist-info/METADATA
j4useragent-0.1.2.dist-info/WHEEL
j4useragent-0.1.2.dist-info/top_level.txt
j4useragent-0.1.2.dist-info/RECORD
